setup.py
test/test_packaging.py
yinstruments/__init__.py
yinstruments/async_reader.py
yinstruments/powersupply.py
yinstruments/usb_finder.py
yinstruments/usb_power.py
yinstruments.egg-info/PKG-INFO
yinstruments.egg-info/SOURCES.txt
yinstruments.egg-info/dependency_links.txt
yinstruments.egg-info/entry_points.txt
yinstruments.egg-info/requires.txt
yinstruments.egg-info/top_level.txt
yinstruments/pdu/__init__.py
yinstruments/pdu/cli.py
yinstruments/pdu/lindy.py
yinstruments/pdu/netbooter.py
yinstruments/pdu/pdu.py