Metadata-Version: 2.1
Name: yinstruments
Version: 1.5.0
Summary: Experiment device control scripts for BYU's Configurable Computing Lab (https://ccl.byu.edu/)
Home-page: https://github.com/byuccl/yinstruments
Author: Jeff Goeders
Author-email: jeff.goeders@gmail.com
License: UNKNOWN
Platform: UNKNOWN
